xjet/__init__.py
xjet/api.py
xjet/sync.py
xjet-0.1.5.dist-info/LICENSE
xjet-0.1.5.dist-info/WHEEL
xjet-0.1.5.dist-info/METADATA
xjet-0.1.5.dist-info/RECORD
