Metadata-Version: 2.1
Name: xjet
Version: 0.1.5
Summary: Python SDK for t.me/xJetSwapBot
Home-page: https://t.me/xJetSwapBot
Keywords: ton,xjet,xjetswap,sdk
Author: delpydoc
Author-email: delpydoc@proton.me
Requires-Python: >=3.7,<4.0
Classifier: License :: OSI Approved :: MIT License
Classifier: Operating System :: OS Independent
Classifier: Programming Language :: Python :: 3
Classifier: Programming Language :: Python :: 3.7
Classifier: Programming Language :: Python :: 3.8
Classifier: Programming Language :: Python :: 3.9
Classifier: Programming Language :: Python :: 3.10
Classifier: Programming Language :: Python :: 3.11
Classifier: Programming Language :: Python :: 3
Requires-Dist: ecdsa (>=0.18.0)
Requires-Dist: httpx (>=0.23.1)
Project-URL: Repository, https://github.com/xJetLabs/python-sdk
